MANIFEST.in
README.rst
setup.py
license/COPYING
license/lgpl-2.1.txt
test/test_doc.py
test/test_indentation.py
test/test_simpledoc.py
yattag/__init__.py
yattag/doc.py
yattag/indentation.py
yattag/py.typed
yattag/simpledoc.py
yattag.egg-info/PKG-INFO
yattag.egg-info/SOURCES.txt
yattag.egg-info/dependency_links.txt
yattag.egg-info/requires.txt
yattag.egg-info/top_level.txt